lektor_strip_html_tags.py
lektor_strip_html_tags-0.3.1.dist-info/LICENSE
lektor_strip_html_tags-0.3.1.dist-info/METADATA
lektor_strip_html_tags-0.3.1.dist-info/WHEEL
lektor_strip_html_tags-0.3.1.dist-info/entry_points.txt
lektor_strip_html_tags-0.3.1.dist-info/top_level.txt
lektor_strip_html_tags-0.3.1.dist-info/RECORD
