Metadata-Version: 2.1
Name: lektor-strip-html-tags
Version: 0.3.1
Summary: Strip HTML tags, effectively turning HTML into plain text.
Home-page: https://github.com/terminal-labs/lektor-strip-html-tags
Author: Terminal Labs
Author-email: solutions@terminallabs.com
License: BSD-3-Clause
Keywords: Lektor plugin html static-site regex jinja2 jinja filter
Platform: UNKNOWN
Classifier: Environment :: Plugins
Classifier: Environment :: Web Environment
Classifier: Framework :: Lektor
Classifier: License :: OSI Approved :: BSD License
